pypwdft/__init__.py
pypwdft/_version.py
pypwdft/psystem.py
pypwdft/pypwdft.py
pypwdft/system_builder.py
pypwdft/molecules/benzene.xyz
pypwdft/molecules/bf3.xyz
pypwdft/molecules/ch4.xyz
pypwdft/molecules/co.xyz
pypwdft/molecules/co2.xyz
pypwdft/molecules/ethylene.xyz
pypwdft/molecules/h2.xyz
pypwdft/molecules/h2o.xyz
pypwdft/molecules/he.xyz
pypwdft/molecules/lih.xyz
pypwdft/molecules/nh3.xyz
pypwdft-0.2.0.dist-info/LICENSE
pypwdft-0.2.0.dist-info/METADATA
pypwdft-0.2.0.dist-info/WHEEL
pypwdft-0.2.0.dist-info/top_level.txt
pypwdft-0.2.0.dist-info/RECORD
