Metadata-Version: 2.1
Name: pypwdft
Version: 0.2.0
Summary: pypwdft
Home-page: https://www.github.com/ifilot/pypwdft
Author: Ivo Filot
Author-email: Ivo Filot <i.a.w.filot@tue.nl>
Maintainer-email: Ivo Filot <i.a.w.filot@tue.nl>
License: GPL-3.0-or-later
Project-URL: Homepage, https://www.github.com/ifilot/pypwdft
Project-URL: Bug Tracker, https://www.github.com/ifilot/pypwdft/issues
Classifier: Programming Language :: Python :: 3
Classifier: Operating System :: OS Independent
Requires-Python: >=3.5
License-File: LICENSE
Requires-Dist: scipy
Requires-Dist: numpy
Requires-Dist: mendeleev
Requires-Dist: pyfftw
